{
  "name": "faust_matrix_diffusion_gcn_512",
  "model_type": null,
  "timestamp": "2026-07-17T18:57:14+00:00",
  "git_commit": "2eacc88",
  "device": "cuda",
  "networks": {
    "extractor": {
      "class": "GCNFeatureExtractor",
      "num_params": 51504,
      "num_trainable": 51504
    },
    "denoiser": {
      "class": "MatrixDenoiser",
      "num_params": 3644209,
      "num_trainable": 3644209
    }
  },
  "config": {
    "name": "faust_matrix_diffusion_gcn_512",
    "is_train": true,
    "path": {
      "resume_state": "extractor_faust.pth",
      "resume": false,
      "experiment_root": "/data2/home/jrr25/Documents/shape-match-diffusion/experiments/faust_matrix_diffusion_gcn_512",
      "models": "/data2/home/jrr25/Documents/shape-match-diffusion/experiments/faust_matrix_diffusion_gcn_512/models",
      "results": "/data2/home/jrr25/Documents/shape-match-diffusion/experiments/faust_matrix_diffusion_gcn_512/results"
    },
    "datasets": {
      "train": {
        "name": "Faust_r",
        "type": "SparsePairFaustDataset",
        "phase": "train",
        "n_sparse": 512
      },
      "val": {
        "name": "Faust_r",
        "type": "SparsePairFaustDataset",
        "phase": "test",
        "n_sparse": 512,
        "exclude_self": true
      },
      "test": {
        "name": "Faust_r",
        "type": "SparsePairFaustDataset",
        "phase": "test",
        "n_sparse": 512,
        "exclude_self": true,
        "ret_evecs": true,
        "num_evecs": 200
      }
    },
    "networks": {
      "extractor": {
        "type": "GCNFeatureExtractor",
        "out_dim": 128,
        "node_in": "xyz",
        "hidden": [
          16,
          32,
          64
        ],
        "hops": [
          1,
          2,
          3,
          4
        ],
        "patch_size": 64,
        "knn": 8
      },
      "denoiser": {
        "type": "MatrixDenoiser",
        "feat_dim": 128,
        "dim": 128,
        "heads": 4,
        "depth": 6,
        "n_anchors": 16,
        "dropout": 0.0
      }
    },
    "diffusion": {
      "eta": 0.1,
      "proj_iters": 6,
      "schedule_s": 0.008,
      "sample_steps": 50,
      "final_iters": 20
    },
    "densifier": {
      "type": "ZoomOutDensifier",
      "k_start": 20,
      "k_step": 10,
      "k_final": 200
    },
    "eval": {
      "sparse": true,
      "dense": false
    },
    "train": {
      "total_epochs": 30,
      "log_freq": 20,
      "optims": {
        "extractor": {
          "type": "AdamW",
          "lr": 0.0001,
          "weight_decay": 0.0001
        },
        "denoiser": {
          "type": "AdamW",
          "lr": 0.001,
          "weight_decay": 0.0001
        }
      },
      "schedulers": {
        "extractor": {
          "type": "CosineAnnealingLR",
          "eta_min": 1e-05,
          "T_max": 30
        },
        "denoiser": {
          "type": "CosineAnnealingLR",
          "eta_min": 0.0001,
          "T_max": 30
        }
      }
    },
    "val": {
      "subset": 40
    }
  }
}